[
  {
    "op": "core/column-removal",
    "columnName": "PROVINCIA",
    "description": "Remove column PROVINCIA"
  },
  {
    "op": "core/column-removal",
    "columnName": "MUNICIPIO",
    "description": "Remove column MUNICIPIO"
  },
  {
    "op": "core/column-removal",
    "columnName": "PUNTO_MUESTREO",
    "description": "Remove column PUNTO_MUESTREO"
  },
  {
    "op": "core/column-removal",
    "columnName": "V01",
    "description": "Remove column V01"
  },
  {
    "op": "core/column-removal",
    "columnName": "V02",
    "description": "Remove column V02"
  },
  {
    "op": "core/column-removal",
    "columnName": "V03",
    "description": "Remove column V03"
  },
  {
    "op": "core/column-removal",
    "columnName": "V04",
    "description": "Remove column V04"
  },
  {
    "op": "core/column-removal",
    "columnName": "V05",
    "description": "Remove column V05"
  },
  {
    "op": "core/column-removal",
    "columnName": "V06",
    "description": "Remove column V06"
  },
  {
    "op": "core/column-removal",
    "columnName": "V07",
    "description": "Remove column V07"
  },
  {
    "op": "core/column-removal",
    "columnName": "V08",
    "description": "Remove column V08"
  },
  {
    "op": "core/column-removal",
    "columnName": "V09",
    "description": "Remove column V09"
  },
  {
    "op": "core/column-removal",
    "columnName": "V10",
    "description": "Remove column V10"
  },
  {
    "op": "core/column-removal",
    "columnName": "V11",
    "description": "Remove column V11"
  },
  {
    "op": "core/column-removal",
    "columnName": "V12",
    "description": "Remove column V12"
  },
  {
    "op": "core/column-removal",
    "columnName": "V13",
    "description": "Remove column V13"
  },
  {
    "op": "core/column-removal",
    "columnName": "V14",
    "description": "Remove column V14"
  },
  {
    "op": "core/column-removal",
    "columnName": "V15",
    "description": "Remove column V15"
  },
  {
    "op": "core/column-removal",
    "columnName": "V16",
    "description": "Remove column V16"
  },
  {
    "op": "core/column-removal",
    "columnName": "V17",
    "description": "Remove column V17"
  },
  {
    "op": "core/column-removal",
    "columnName": "V18",
    "description": "Remove column V18"
  },
  {
    "op": "core/column-removal",
    "columnName": "V19",
    "description": "Remove column V19"
  },
  {
    "op": "core/column-removal",
    "columnName": "V20",
    "description": "Remove column V20"
  },
  {
    "op": "core/column-removal",
    "columnName": "V21",
    "description": "Remove column V21"
  },
  {
    "op": "core/column-removal",
    "columnName": "V22",
    "description": "Remove column V22"
  },
  {
    "op": "core/column-removal",
    "columnName": "V23",
    "description": "Remove column V23"
  },
  {
    "op": "core/column-removal",
    "columnName": "V24",
    "description": "Remove column V24"
  }
]